[{"type":"enemy","hp":[34,35],"attack":[15,15],"speed":[0.8125,0.84375]},{"type":"enemy","hp":[24,35],"attack":[11,12],"speed":[0.5,0.84375]},{"type":"enemy","hp":[21,36],"attack":[15,15],"speed":[0.40625,0.875]},{"type":"enemy","hp":[31,53],"attack":[7,15],"speed":[0.71875,1.40625]},{"type":"enemy","hp":[37,58],"attack":[7,10],"speed":[0.90625,1.5625]},{"type":"enemy","hp":[16,46],"attack":[15,15],"speed":[0.25,1.1875]},{"type":"enemy","hp":[23,70],"attack":[10,15],"speed":[0.46875,1.9375]},{"type":"boss","hp":[86,100],"attack":[19,20],"speed":[0.3,1]}]