{"frames":{"cannon_Lipstick_empty":{"frame":{"x":2,"y":2,"w":371,"h":836},"rotated":false,"trimmed":false,"spriteSourceSize":{"x":0,"y":0,"w":371,"h":836},"sourceSize":{"w":371,"h":836},"pivot":{"x":0.5,"y":0.5}},"FabulousHorseLogo_Final":{"frame":{"x":377,"y":2,"w":829,"h":438},"rotated":false,"trimmed":false,"spriteSourceSize":{"x":0,"y":0,"w":829,"h":438},"sourceSize":{"w":829,"h":438},"pivot":{"x":0.5,"y":0.5}},"modal1":{"frame":{"x":2,"y":842,"w":636,"h":527},"rotated":false,"trimmed":false,"spriteSourceSize":{"x":0,"y":0,"w":636,"h":527},"sourceSize":{"w":636,"h":527},"pivot":{"x":0.5,"y":0.5}},"rocket-button":{"frame":{"x":642,"y":444,"w":517,"h":425},"rotated":false,"trimmed":false,"spriteSourceSize":{"x":0,"y":0,"w":517,"h":425},"sourceSize":{"w":517,"h":425},"pivot":{"x":0.5,"y":0.5}},"jump-button":{"frame":{"x":642,"y":873,"w":470,"h":327},"rotated":false,"trimmed":false,"spriteSourceSize":{"x":0,"y":0,"w":470,"h":327},"sourceSize":{"w":470,"h":327},"pivot":{"x":0.5,"y":0.5}},"button":{"frame":{"x":1210,"y":2,"w":407,"h":169},"rotated":false,"trimmed":false,"spriteSourceSize":{"x":0,"y":0,"w":407,"h":169},"sourceSize":{"w":407,"h":169},"pivot":{"x":0.5,"y":0.5}},"cannon_Wheel":{"frame":{"x":1210,"y":175,"w":398,"h":398},"rotated":false,"trimmed":false,"spriteSourceSize":{"x":0,"y":0,"w":398,"h":398},"sourceSize":{"w":398,"h":398},"pivot":{"x":0.5,"y":0.5}}},"meta":{"app":"http://github.com/odrick/free-tex-packer-core","version":"0.3.4","image":"horse@1x.png","format":"RGBA8888","size":{"w":1619,"h":1371},"scale":1}}